average_decision_ordering/__init__.py
average_decision_ordering/test.py
average_decision_ordering-1.0.dist-info/METADATA
average_decision_ordering-1.0.dist-info/WHEEL
average_decision_ordering-1.0.dist-info/top_level.txt
average_decision_ordering-1.0.dist-info/RECORD
