Metadata-Version: 2.1
Name: average-decision-ordering
Version: 1.0
Summary: Calculates the average decision ordering metric
Home-page: http://github.com/tfaucett/average_decision_ordering
Author: Taylor Faucett
Author-email: tfaucett@uci.edu
License: MIT
Keywords: statistics,physics,math
Platform: UNKNOWN
Classifier: Programming Language :: Python :: 2
Classifier: Programming Language :: Python :: 3
Classifier: Topic :: Scientific/Engineering :: Mathematics
Classifier: Intended Audience :: Developers
Classifier: Intended Audience :: Education
Classifier: Intended Audience :: End Users/Desktop
Classifier: Intended Audience :: Science/Research
Classifier: Operating System :: MacOS
Classifier: Operating System :: Unix
Classifier: Topic :: Education
Classifier: Topic :: Utilities
Requires-Dist: numpy
Requires-Dist: pandas
